Log.py
exem_logs-1.3.0.dist-info/METADATA
exem_logs-1.3.0.dist-info/WHEEL
exem_logs-1.3.0.dist-info/top_level.txt
exem_logs-1.3.0.dist-info/RECORD
